retention_rules/__init__.py
retention_rules/builder.py
retention_rules/periods.py
retention_rules/policy.py
retention_rules-0.1.1.dist-info/LICENSE
retention_rules-0.1.1.dist-info/METADATA
retention_rules-0.1.1.dist-info/WHEEL
retention_rules-0.1.1.dist-info/top_level.txt
retention_rules-0.1.1.dist-info/RECORD
