Metadata-Version: 2.1
Name: retention-rules
Version: 0.1.1
Summary: A library to calculate period-based retention rules for timestamps
Author: Matt Jarvis
Project-URL: Homepage, https://github.com/mattj23/retention-rules
Classifier: Development Status :: 3 - Alpha
Classifier: Intended Audience :: Developers
Classifier: License :: OSI Approved :: MIT License
Classifier: Programming Language :: Python :: 3
Requires-Python: >=3.7
License-File: LICENSE
